{
  "lives": [
    {
      "name": "aktv",
      "type": 0,
      "url": "http://aktv.top/live.m3u",
      "epg": "http://epg.112114.xyz/?ch={name}&date={date}",
      "logo": "https://epg.112114.xyz/logo/{name}.png"
    }, 
    {
      "name": "综合",
      "type": 0,
      "url": "https://video.mytvsuper.xyz/playlist/zong-he-ding-yue.m3u?token=395626593195248",
      "epg": "http://epg.112114.xyz/?ch={name}&date={date}",
      "logo": "https://epg.112114.xyz/logo/{name}.png"
    },
    {
      "name": "体育",
      "type": 0,
      "url": "https://video.mytvsuper.xyz/playlist/ti-yu-ding-yue.m3u?token=395626593195248",
      "epg": "http://epg.112114.xyz/?ch={name}&date={date}",
      "logo": "https://epg.112114.xyz/logo/{name}.png"
    },
    {
      "name": "央视",
      "type": 0,
      "url": "https://video.mytvsuper.xyz/playlist/yang-shi-wei-shi.m3u?token=395626593195248",
      "epg": "http://epg.112114.xyz/?ch={name}&date={date}",
      "logo": "https://epg.112114.xyz/logo/{name}.png"
    },
    {
      "name": "365直播",
      "type": 0,
      "url": "https://live.iptv365.org/live.m3u",
      "epg": "http://epg.112114.xyz/?ch={name}&date={date}",
      "logo": "https://epg.112114.xyz/logo/{name}.png"
    },
    {
      "name": "zjykfy",
      "type": 0,
      "url": "https://ghproxy.cc/https://raw.githubusercontent.com/zjykfy/yy-ff-yy/c702b5d9c9014a90a17a15275afa0cc6b812e2cc/all.m3u",
      "epg": "http://epg.112114.xyz/?ch={name}&date={date}",
      "logo": "https://epg.112114.xyz/logo/{name}.png"
    },
    {
      "name": "tt",
      "type": 0,
      "url": "https://raw.githubusercontent.com/j67001/test/80947719f2f943c168c4e6807b436b9f59a60bf3/tt.swf",
      "epg": "http://epg.112114.xyz/?ch={name}&date={date}",
      "logo": "https://epg.112114.xyz/logo/{name}.png"
    },
    {
      "name": "live",
      "type": 0,
      "url": "https://ghproxy.cc/https://raw.githubusercontent.com/cqbf/tv/refs/heads/main/live.m3u",
      "epg": "http://epg.112114.xyz/?ch={name}&date={date}",
      "logo": "https://epg.112114.xyz/logo/{name}.png"
    }
  ]
}
